itch/__init__.py
itch/indicators.py
itch/messages.py
itch/parser.py
itchfeed-1.0.5.dist-info/licenses/LICENSE
itchfeed-1.0.5.dist-info/METADATA
itchfeed-1.0.5.dist-info/WHEEL
itchfeed-1.0.5.dist-info/top_level.txt
itchfeed-1.0.5.dist-info/RECORD
