Metadata-Version: 2.4
Name: itchfeed
Version: 1.0.5
Summary: Simple parser for ITCH messages
Home-page: https://github.com/bbalouki/itch
Download-URL: https://pypi.org/project/itchfeed/
Author: Bertin Balouki SIMYELI
Author-email: <bertin@bbstrader.com>
Maintainer: Bertin Balouki SIMYELI
License: The MIT License (MIT)
Project-URL: Source Code, https://github.com/bbalouki/itch
Keywords: Finance,Financial,Quantitative,Equities,Totalview-ITCH,Totalview,Nasdaq-ITCH,Nasdaq,ITCH,Data,Feed,ETFs,Funds,Trading,Investing
Classifier: Development Status :: 5 - Production/Stable
Classifier: Intended Audience :: Developers
Classifier: Intended Audience :: Financial and Insurance Industry
Classifier: Topic :: Office/Business :: Financial :: Investment
Classifier: Programming Language :: Python :: 3
Classifier: Operating System :: OS Independent
License-File: LICENSE
Requires-Dist: pytest
Dynamic: author
Dynamic: author-email
Dynamic: classifier
Dynamic: description
Dynamic: description-content-type
Dynamic: download-url
Dynamic: home-page
Dynamic: keywords
Dynamic: license
Dynamic: license-file
Dynamic: maintainer
Dynamic: project-url
Dynamic: requires-dist
Dynamic: summary
